spotted/__init__.py
spotted/__main__.py
spotted/_version.py
spotted/config/db/db_test.sql
spotted/config/db/post_db_del.sql
spotted/config/db/post_db_init.sql
spotted/config/markdown/anonym_names.md
spotted/config/markdown/help.md
spotted/config/markdown/instructions.md
spotted/config/markdown/no_strings.md
spotted/config/markdown/report_cancel.md
spotted/config/markdown/rules.md
spotted/config/markdown/spot_cancel.md
spotted/config/markdown/start.md
spotted/config/yaml/autoreplies.yaml
spotted/config/yaml/settings.yaml
spotted/config/yaml/settings.yaml.types
spotted/data/__init__.py
spotted/data/config.py
spotted/data/data_reader.py
spotted/data/db_manager.py
spotted/data/pending_post.py
spotted/data/post_data.py
spotted/data/published_post.py
spotted/data/report.py
spotted/data/user.py
spotted/debug/__init__.py
spotted/debug/log_manager.py
spotted/handlers/__init__.py
spotted/handlers/anonym_comment.py
spotted/handlers/approve.py
spotted/handlers/autoreply.py
spotted/handlers/ban.py
spotted/handlers/cancel.py
spotted/handlers/clean_pending.py
spotted/handlers/constants.py
spotted/handlers/db_backup.py
spotted/handlers/follow_comment.py
spotted/handlers/follow_spot.py
spotted/handlers/forwarded_post.py
spotted/handlers/help.py
spotted/handlers/job_handlers.py
spotted/handlers/purge.py
spotted/handlers/reload.py
spotted/handlers/reply.py
spotted/handlers/report_spot.py
spotted/handlers/report_user.py
spotted/handlers/rules.py
spotted/handlers/sban.py
spotted/handlers/settings.py
spotted/handlers/spot.py
spotted/handlers/start.py
spotted/scripts/f_crypto.py
spotted/scripts/run_sql.py
spotted/utils/__init__.py
spotted/utils/constants.py
spotted/utils/conversation_util.py
spotted/utils/info_util.py
spotted/utils/keyboard_util.py
telegram_spotted_dmi_bot-3.1.0.dist-info/LICENSE
telegram_spotted_dmi_bot-3.1.0.dist-info/METADATA
telegram_spotted_dmi_bot-3.1.0.dist-info/WHEEL
telegram_spotted_dmi_bot-3.1.0.dist-info/entry_points.txt
telegram_spotted_dmi_bot-3.1.0.dist-info/top_level.txt
telegram_spotted_dmi_bot-3.1.0.dist-info/RECORD
