Metadata-Version: 2.1
Name: telegram-spotted-dmi-bot
Version: 3.1.0
Summary: Telegram-SpottedDMI-Bot is the platform that powers @Spotted_DMI_Bot, a Telegram bot that let students send an anonymous message to the channel community
Author: drendog, Helias, Herbrant, alepiaz, TaToTanWeb, FilippoMarletta
Author-email: TendTo <casablancaerneto@gmail.com>
Maintainer: drendog, Helias, alepiaz, TaToTanWeb
Maintainer-email: TendTo <casablancaerneto@gmail.com>
License: GNU GENERAL PUBLIC LICENSE
Project-URL: Homepage, https://unict-dmi.github.io/Telegram-SpottedDMI-Bot/
Project-URL: Documentation, https://unict-dmi.github.io/Telegram-SpottedDMI-Bot/api/modules
Project-URL: Repository, https://github.com/UNICT-DMI/Telegram-SpottedDMI-Bot
Project-URL: Changelog, https://github.com/UNICT-DMI/Telegram-SpottedDMI-Bot/blob/main/.github/CHANGELOG.md
Keywords: python,telegram,bot,spotted,dmi,unict
Classifier: Development Status :: 5 - Production/Stable
Classifier: Programming Language :: Python
Classifier: License :: OSI Approved :: MIT License
Classifier: Intended Audience :: Developers
Classifier: Intended Audience :: Education
Classifier: Topic :: Communications :: Chat
Classifier: Operating System :: OS Independent
Requires-Python: >=3.10
License-File: LICENSE
Requires-Dist: APScheduler ==3.10.4
Requires-Dist: cryptography ==42.0.2
Requires-Dist: python-telegram-bot ==20.8
Requires-Dist: pytz ==2023.3.post1
Requires-Dist: PyYAML ==6.0.1
Provides-Extra: lint
Requires-Dist: pylint ; extra == 'lint'
Requires-Dist: black ; extra == 'lint'
Requires-Dist: isort ; extra == 'lint'
Provides-Extra: test
Requires-Dist: pytest ; extra == 'test'
Requires-Dist: pytest-asyncio ; extra == 'test'
Requires-Dist: pytest-cov ; extra == 'test'
Requires-Dist: pytest-mock ; extra == 'test'
